{"data":{"email":"andres-network@hotmail.com","username":"Andresdst","certificates":[{"score":10,"code":"7c617acb-5648-438d-8112-899d3e57b683","title":"Curso Profesional de JavaScript"},{"score":9,"code":"f175eedf-4894-4355-954c-dc1568d98785","title":"Curso de introducción a la programación"},{"score":9,"code":"09ef807a-9538-4bc7-a896-ef4819347bb6","title":"Curso profesional de PHP"}],"articles":[],"courses":[{"title":"Curso Profesional de JavaScript","progress":"100.0","url":"http://codigofacilito.com/courses/javascript-profesional"},{"title":"JavaScript y el DOM","progress":"100.0","url":"http://codigofacilito.com/courses/javascript-dom"},{"title":"Curso profesional de PHP","progress":"100.0","url":"http://codigofacilito.com/courses/php-profesional"},{"title":"El glosario del JAMStack","progress":"100.0","url":"http://codigofacilito.com/courses/glosario-jamstack"},{"title":"Pruebas unitarias con PHP","progress":"5.0","url":"http://codigofacilito.com/courses/php-testing"},{"title":"Curso de introducción a la programación","progress":"100.0","url":"http://codigofacilito.com/courses/introduccion"},{"title":"Curso para crear un juego con Pygame","progress":"1.0","url":"http://codigofacilito.com/courses/pygame-videojuego"},{"title":"Crea un sitio personal con Gatsby","progress":"100.0","url":"http://codigofacilito.com/courses/sitio-persional-gatsby"},{"title":"Curso de introducción a los Algoritmos","progress":"100.0","url":"http://codigofacilito.com/courses/algoritmos"},{"title":"Curso de Docker","progress":"4.0","url":"http://codigofacilito.com/courses/docker"}],"finished_courses":[{"title":"Curso Profesional de JavaScript","url":"http://codigofacilito.com/courses/javascript-profesional"},{"title":"JavaScript y el DOM","url":"http://codigofacilito.com/courses/javascript-dom"},{"title":"Curso profesional de PHP","url":"http://codigofacilito.com/courses/php-profesional"},{"title":"El glosario del JAMStack","url":"http://codigofacilito.com/courses/glosario-jamstack"},{"title":"Curso de introducción a la programación","url":"http://codigofacilito.com/courses/introduccion"},{"title":"Crea un sitio personal con Gatsby","url":"http://codigofacilito.com/courses/sitio-persional-gatsby"},{"title":"Curso de introducción a los Algoritmos","url":"http://codigofacilito.com/courses/algoritmos"}]},"errors":[]}